.editorconfig
.gitignore
.gitlab-ci.yml
README.rst
publish.settings.sh
publish.sh
pyproject.toml
tsconfig.json
.idea/modules.xml
.idea/peek-core-user.iml
.idea/inspectionProfiles/Project_Default.xml
.idea/inspectionProfiles/profiles_settings.xml
docker-ldap/Dockerfile
docker-ldap/build-and-run.sh
docker-ldap/entrypoint.sh
docker-ldap/ldapsearch.sh
docker-ldap/supervisord.conf
docker-ldap/test-samba.sh
peek_core_user/PlatformDependencyTest.py
peek_core_user/TempUnitTest.py
peek_core_user/__init__.py
peek_core_user/plugin_package.json
peek_core_user.egg-info/PKG-INFO
peek_core_user.egg-info/SOURCES.txt
peek_core_user.egg-info/dependency_links.txt
peek_core_user.egg-info/requires.txt
peek_core_user.egg-info/top_level.txt
peek_core_user/_private/PluginNames.py
peek_core_user/_private/__init__.py
peek_core_user/_private/alembic.ini
peek_core_user/_private/admin-app/user.module.ts
peek_core_user/_private/admin-app/components/core-user-page/core-user-page.component.html
peek_core_user/_private/admin-app/components/core-user-page/core-user-page.component.scss
peek_core_user/_private/admin-app/components/core-user-page/core-user-page.component.ts
peek_core_user/_private/admin-app/components/edit-internal-group/edit-internal-group.component.html
peek_core_user/_private/admin-app/components/edit-internal-group/edit-internal-group.component.scss
peek_core_user/_private/admin-app/components/edit-internal-group/edit-internal-group.component.ts
peek_core_user/_private/admin-app/components/edit-internal-user/edit-internal-user.component.html
peek_core_user/_private/admin-app/components/edit-internal-user/edit-internal-user.component.scss
peek_core_user/_private/admin-app/components/edit-internal-user/edit-internal-user.component.ts
peek_core_user/_private/admin-app/components/edit-ldap-setting/edit-ldap-setting.component.html
peek_core_user/_private/admin-app/components/edit-ldap-setting/edit-ldap-setting.component.scss
peek_core_user/_private/admin-app/components/edit-ldap-setting/edit-ldap-setting.component.ts
peek_core_user/_private/admin-app/components/edit-otp/edit.component.html
peek_core_user/_private/admin-app/components/edit-otp/edit.component.scss
