Metadata-Version: 2.4
Name: peek-core-user
Version: 5.1.4
Summary: Peek Core User - Peek's user management plugin
Author-email: Synerty <contact@synerty.com>
Project-URL: Homepage, https://github.com/Synerty/peek-core-user
Keywords: Peek,Python,Platform,synerty
Requires-Dist: peek-plugin-base==5.1.4
Requires-Dist: python-ldap
